celgcp/__init__.py
celgcp/celgcp.py
celgcp-1.1.2.dist-info/LICENSE.md
celgcp-1.1.2.dist-info/METADATA
celgcp-1.1.2.dist-info/WHEEL
celgcp-1.1.2.dist-info/RECORD
