Metadata-Version: 2.1
Name: celgcp
Version: 1.1.2
Summary: This module allows to evaluate the Google Cloud IAM Conditions where CEL is the expression language.
Home-page: https://github.com/hm98765/celgcp/
Author: hm98765
Author-email: hm98765@github.com
Requires-Python: >=3.9,<4.0
Classifier: Programming Language :: Python :: 3
Classifier: Programming Language :: Python :: 3.9
Classifier: Programming Language :: Python :: 3.10
Classifier: Programming Language :: Python :: 3.11
Classifier: Programming Language :: Python :: 3.12
Requires-Dist: cel-python (>=0.1.5,<0.2.0)
Project-URL: Repository, https://github.com/hm98765/celgcp/
